ReactNativeTraining/README.md
ReactNativeTraining/__init__.py
ReactNativeTraining/__main__.py
ReactNativeTraining/file.epub
ReactNativeTraining/index.html
ReactNativeTraining/css/__init__.py
ReactNativeTraining/css/annotations.css
ReactNativeTraining/css/main.css
ReactNativeTraining/css/normalize.css
ReactNativeTraining/css/popup.css
ReactNativeTraining/font/__init__.py
ReactNativeTraining/font/fontello.eot
ReactNativeTraining/font/fontello.svg
ReactNativeTraining/font/fontello.ttf
ReactNativeTraining/font/fontello.woff
ReactNativeTraining/img/__init__.py
ReactNativeTraining/img/annotator-glyph-sprite.png
ReactNativeTraining/img/annotator-icon-sprite.png
ReactNativeTraining/img/apple-touch-icon.png
ReactNativeTraining/img/cancelfullscreen.png
ReactNativeTraining/img/close.png
ReactNativeTraining/img/fullscreen.png
ReactNativeTraining/img/loader.gif
ReactNativeTraining/img/menu-icon.png
ReactNativeTraining/img/save.png
ReactNativeTraining/img/saved.png
ReactNativeTraining/img/settings-s.png
ReactNativeTraining/img/settings.png
ReactNativeTraining/img/star.png
ReactNativeTraining/js/__init__.py
ReactNativeTraining/js/epub.js
ReactNativeTraining/js/epub.min.js
ReactNativeTraining/js/epub.min.map
ReactNativeTraining/js/hooks.min.js
ReactNativeTraining/js/hooks.min.map
ReactNativeTraining/js/reader.js
ReactNativeTraining/js/reader.js.map
ReactNativeTraining/js/reader.min.js
ReactNativeTraining/js/reader.min.map
ReactNativeTraining/js/hooks/__init__.py
ReactNativeTraining/js/hooks/extensions/__init__.py
ReactNativeTraining/js/hooks/extensions/highlight.js
ReactNativeTraining/js/libs/__init__.py
ReactNativeTraining/js/libs/jquery.min.js
ReactNativeTraining/js/libs/localforage.min.js
ReactNativeTraining/js/libs/screenfull.js
ReactNativeTraining/js/libs/screenfull.min.js
ReactNativeTraining/js/libs/zip.min.js
ReactNativeTraining/js/plugins/__init__.py
ReactNativeTraining/js/plugins/hypothesis.js
ReactNativeTraining/js/plugins/search.js
react_native_training-2024.3.3.0.dist-info/METADATA
react_native_training-2024.3.3.0.dist-info/WHEEL
react_native_training-2024.3.3.0.dist-info/entry_points.txt
react_native_training-2024.3.3.0.dist-info/top_level.txt
react_native_training-2024.3.3.0.dist-info/RECORD
